packagelib/__init__.py
packagelib/main.py
packagelib-0.1.8.dist-info/METADATA
packagelib-0.1.8.dist-info/WHEEL
packagelib-0.1.8.dist-info/licenses/LICENSE
packagelib-0.1.8.dist-info/RECORD
