Metadata-Version: 2.1
Name: packagelib
Version: 0.1.8
Summary: Create and publish your own packages within Python!
Project-URL: Homepage, https://github.com/Minetezter/packagelib
Project-URL: Bug Tracker, https://github.com/Minetezter/packagelib/issues
Author-email: minetezter <minetezter@protonmail.net>
License-File: LICENSE
Classifier: License :: OSI Approved :: GNU Affero General Public License v3 or later (AGPLv3+)
Classifier: Operating System :: POSIX :: Linux
Classifier: Programming Language :: Python :: 3
Requires-Python: >=3.7
Requires-Dist: build>=0.10.0
Requires-Dist: twine>=3.8.0
